{"kind":"symbol","hierarchy":{"paths":[["doc:\/\/yubikit-swift.YubiKit\/documentation\/YubiKit","doc:\/\/yubikit-swift.YubiKit\/documentation\/YubiKit\/CTAP2","doc:\/\/yubikit-swift.YubiKit\/documentation\/YubiKit\/CTAP2\/MakeCredential","doc:\/\/yubikit-swift.YubiKit\/documentation\/YubiKit\/CTAP2\/MakeCredential\/Parameters"]]},"schemaVersion":{"major":0,"patch":0,"minor":3},"sections":[],"variants":[{"traits":[{"interfaceLanguage":"swift"}],"paths":["\/documentation\/yubikit\/ctap2\/makecredential\/parameters\/init(clientdatahash:rp:user:pubkeycredparams:excludelist:extensions:options:enterpriseattestation:)"]}],"primaryContentSections":[{"declarations":[{"languages":["swift"],"tokens":[{"text":"init","kind":"keyword"},{"text":"(","kind":"text"},{"text":"clientDataHash","kind":"externalParam"},{"text":": ","kind":"text"},{"preciseIdentifier":"s:10Foundation4DataV","text":"Data","kind":"typeIdentifier"},{"text":", ","kind":"text"},{"text":"rp","kind":"externalParam"},{"text":": ","kind":"text"},{"preciseIdentifier":"s:7YubiKit8WebAuthnO","identifier":"doc:\/\/yubikit-swift.YubiKit\/documentation\/YubiKit\/WebAuthn","text":"WebAuthn","kind":"typeIdentifier"},{"text":".","kind":"text"},{"preciseIdentifier":"s:7YubiKit8WebAuthnO19PublicKeyCredentialO","identifier":"doc:\/\/yubikit-swift.YubiKit\/documentation\/YubiKit\/WebAuthn\/PublicKeyCredential","text":"PublicKeyCredential","kind":"typeIdentifier"},{"text":".","kind":"text"},{"preciseIdentifier":"s:7YubiKit8WebAuthnO19PublicKeyCredentialO8RPEntityV","identifier":"doc:\/\/yubikit-swift.YubiKit\/documentation\/YubiKit\/WebAuthn\/PublicKeyCredential\/RPEntity","text":"RPEntity","kind":"typeIdentifier"},{"text":", ","kind":"text"},{"text":"user","kind":"externalParam"},{"text":": ","kind":"text"},{"preciseIdentifier":"s:7YubiKit8WebAuthnO","identifier":"doc:\/\/yubikit-swift.YubiKit\/documentation\/YubiKit\/WebAuthn","text":"WebAuthn","kind":"typeIdentifier"},{"text":".","kind":"text"},{"preciseIdentifier":"s:7YubiKit8WebAuthnO19PublicKeyCredentialO","identifier":"doc:\/\/yubikit-swift.YubiKit\/documentation\/YubiKit\/WebAuthn\/PublicKeyCredential","text":"PublicKeyCredential","kind":"typeIdentifier"},{"text":".","kind":"text"},{"preciseIdentifier":"s:7YubiKit8WebAuthnO19PublicKeyCredentialO10UserEntityV","identifier":"doc:\/\/yubikit-swift.YubiKit\/documentation\/YubiKit\/WebAuthn\/PublicKeyCredential\/UserEntity","text":"UserEntity","kind":"typeIdentifier"},{"text":", ","kind":"text"},{"text":"pubKeyCredParams","kind":"externalParam"},{"text":": [","kind":"text"},{"preciseIdentifier":"s:7YubiKit4COSEO","identifier":"doc:\/\/yubikit-swift.YubiKit\/documentation\/YubiKit\/COSE","text":"COSE","kind":"typeIdentifier"},{"text":".","kind":"text"},{"preciseIdentifier":"s:7YubiKit4COSEO9AlgorithmO","identifier":"doc:\/\/yubikit-swift.YubiKit\/documentation\/YubiKit\/COSE\/Algorithm","text":"Algorithm","kind":"typeIdentifier"},{"text":"], ","kind":"text"},{"text":"excludeList","kind":"externalParam"},{"text":": [","kind":"text"},{"preciseIdentifier":"s:7YubiKit8WebAuthnO","identifier":"doc:\/\/yubikit-swift.YubiKit\/documentation\/YubiKit\/WebAuthn","text":"WebAuthn","kind":"typeIdentifier"},{"text":".","kind":"text"},{"preciseIdentifier":"s:7YubiKit8WebAuthnO19PublicKeyCredentialO","identifier":"doc:\/\/yubikit-swift.YubiKit\/documentation\/YubiKit\/WebAuthn\/PublicKeyCredential","text":"PublicKeyCredential","kind":"typeIdentifier"},{"text":".","kind":"text"},{"preciseIdentifier":"s:7YubiKit8WebAuthnO19PublicKeyCredentialO10DescriptorV","identifier":"doc:\/\/yubikit-swift.YubiKit\/documentation\/YubiKit\/WebAuthn\/PublicKeyCredential\/Descriptor","text":"Descriptor","kind":"typeIdentifier"},{"text":"]? = nil, ","kind":"text"},{"text":"extensions","kind":"externalParam"},{"text":": [","kind":"text"},{"preciseIdentifier":"s:7YubiKit5CTAP2O","identifier":"doc:\/\/yubikit-swift.YubiKit\/documentation\/YubiKit\/CTAP2","text":"CTAP2","kind":"typeIdentifier"},{"text":".","kind":"text"},{"preciseIdentifier":"s:7YubiKit5CTAP2O9ExtensionO","identifier":"doc:\/\/yubikit-swift.YubiKit\/documentation\/YubiKit\/CTAP2\/Extension","text":"Extension","kind":"typeIdentifier"},{"text":".","kind":"text"},{"preciseIdentifier":"s:7YubiKit5CTAP2O9ExtensionO14MakeCredentialO","identifier":"doc:\/\/yubikit-swift.YubiKit\/documentation\/YubiKit\/CTAP2\/Extension\/MakeCredential","text":"MakeCredential","kind":"typeIdentifier"},{"text":".","kind":"text"},{"preciseIdentifier":"s:7YubiKit5CTAP2O9ExtensionO14MakeCredentialO5InputV","identifier":"doc:\/\/yubikit-swift.YubiKit\/documentation\/YubiKit\/CTAP2\/Extension\/MakeCredential\/Input","text":"Input","kind":"typeIdentifier"},{"text":"] = [], ","kind":"text"},{"text":"options","kind":"externalParam"},{"text":": ","kind":"text"},{"preciseIdentifier":"s:7YubiKit5CTAP2O14MakeCredentialO10ParametersV7OptionsV","identifier":"doc:\/\/yubikit-swift.YubiKit\/documentation\/YubiKit\/CTAP2\/MakeCredential\/Parameters\/Options-swift.struct","text":"Options","kind":"typeIdentifier"},{"text":"? = nil, ","kind":"text"},{"text":"enterpriseAttestation","kind":"externalParam"},{"text":": ","kind":"text"},{"preciseIdentifier":"s:Si","text":"Int","kind":"typeIdentifier"},{"text":"? = nil)","kind":"text"}],"platforms":["iOS"]}],"kind":"declarations"}],"metadata":{"fragments":[{"text":"init","kind":"identifier"},{"text":"(","kind":"text"},{"text":"clientDataHash","kind":"externalParam"},{"text":": ","kind":"text"},{"text":"Data","preciseIdentifier":"s:10Foundation4DataV","kind":"typeIdentifier"},{"text":", ","kind":"text"},{"text":"rp","kind":"externalParam"},{"text":": ","kind":"text"},{"text":"WebAuthn","preciseIdentifier":"s:7YubiKit8WebAuthnO","kind":"typeIdentifier"},{"text":".","kind":"text"},{"text":"PublicKeyCredential","preciseIdentifier":"s:7YubiKit8WebAuthnO19PublicKeyCredentialO","kind":"typeIdentifier"},{"text":".","kind":"text"},{"text":"RPEntity","preciseIdentifier":"s:7YubiKit8WebAuthnO19PublicKeyCredentialO8RPEntityV","kind":"typeIdentifier"},{"text":", ","kind":"text"},{"text":"user","kind":"externalParam"},{"text":": ","kind":"text"},{"text":"WebAuthn","preciseIdentifier":"s:7YubiKit8WebAuthnO","kind":"typeIdentifier"},{"text":".","kind":"text"},{"text":"PublicKeyCredential","preciseIdentifier":"s:7YubiKit8WebAuthnO19PublicKeyCredentialO","kind":"typeIdentifier"},{"text":".","kind":"text"},{"text":"UserEntity","preciseIdentifier":"s:7YubiKit8WebAuthnO19PublicKeyCredentialO10UserEntityV","kind":"typeIdentifier"},{"text":", ","kind":"text"},{"text":"pubKeyCredParams","kind":"externalParam"},{"text":": [","kind":"text"},{"text":"COSE","preciseIdentifier":"s:7YubiKit4COSEO","kind":"typeIdentifier"},{"text":".","kind":"text"},{"text":"Algorithm","preciseIdentifier":"s:7YubiKit4COSEO9AlgorithmO","kind":"typeIdentifier"},{"text":"], ","kind":"text"},{"text":"excludeList","kind":"externalParam"},{"text":": [","kind":"text"},{"text":"WebAuthn","preciseIdentifier":"s:7YubiKit8WebAuthnO","kind":"typeIdentifier"},{"text":".","kind":"text"},{"text":"PublicKeyCredential","preciseIdentifier":"s:7YubiKit8WebAuthnO19PublicKeyCredentialO","kind":"typeIdentifier"},{"text":".","kind":"text"},{"text":"Descriptor","preciseIdentifier":"s:7YubiKit8WebAuthnO19PublicKeyCredentialO10DescriptorV","kind":"typeIdentifier"},{"text":"]?, ","kind":"text"},{"text":"extensions","kind":"externalParam"},{"text":": [","kind":"text"},{"text":"CTAP2","preciseIdentifier":"s:7YubiKit5CTAP2O","kind":"typeIdentifier"},{"text":".","kind":"text"},{"text":"Extension","preciseIdentifier":"s:7YubiKit5CTAP2O9ExtensionO","kind":"typeIdentifier"},{"text":".","kind":"text"},{"text":"MakeCredential","preciseIdentifier":"s:7YubiKit5CTAP2O9ExtensionO14MakeCredentialO","kind":"typeIdentifier"},{"text":".","kind":"text"},{"text":"Input","preciseIdentifier":"s:7YubiKit5CTAP2O9ExtensionO14MakeCredentialO5InputV","kind":"typeIdentifier"},{"text":"], ","kind":"text"},{"text":"options","kind":"externalParam"},{"text":": ","kind":"text"},{"text":"Options","preciseIdentifier":"s:7YubiKit5CTAP2O14MakeCredentialO10ParametersV7OptionsV","kind":"typeIdentifier"},{"text":"?, ","kind":"text"},{"text":"enterpriseAttestation","kind":"externalParam"},{"text":": ","kind":"text"},{"text":"Int","preciseIdentifier":"s:Si","kind":"typeIdentifier"},{"text":"?)","kind":"text"}],"roleHeading":"Initializer","externalID":"s:7YubiKit5CTAP2O14MakeCredentialO10ParametersV14clientDataHash2rp4user16pubKeyCredParams11excludeList10extensions7options21enterpriseAttestationAG10Foundation0H0V_AA8WebAuthnO06PublicmE0O8RPEntityVAV10UserEntityVSayAA4COSEO9AlgorithmOGSayAV10DescriptorVGSgSayAC9ExtensionOADO5InputVGAG7OptionsVSgSiSgtcfc","modules":[{"name":"YubiKit"}],"title":"init(clientDataHash:rp:user:pubKeyCredParams:excludeList:extensions:options:enterpriseAttestation:)","symbolKind":"init","role":"symbol"},"identifier":{"url":"doc:\/\/yubikit-swift.YubiKit\/documentation\/YubiKit\/CTAP2\/MakeCredential\/Parameters\/init(clientDataHash:rp:user:pubKeyCredParams:excludeList:extensions:options:enterpriseAttestation:)","interfaceLanguage":"swift"},"references":{"doc://yubikit-swift.YubiKit/documentation/YubiKit/WebAuthn/PublicKeyCredential/Descriptor":{"kind":"symbol","role":"symbol","fragments":[{"text":"struct","kind":"keyword"},{"kind":"text","text":" "},{"kind":"identifier","text":"Descriptor"}],"type":"topic","navigatorTitle":[{"kind":"identifier","text":"Descriptor"}],"url":"\/documentation\/yubikit\/webauthn\/publickeycredential\/descriptor","title":"WebAuthn.PublicKeyCredential.Descriptor","identifier":"doc:\/\/yubikit-swift.YubiKit\/documentation\/YubiKit\/WebAuthn\/PublicKeyCredential\/Descriptor","abstract":[{"type":"text","text":"Public key credential descriptor identifying a specific credential."}]},"doc://yubikit-swift.YubiKit/documentation/YubiKit/CTAP2":{"type":"topic","navigatorTitle":[{"kind":"identifier","text":"CTAP2"}],"fragments":[{"text":"enum","kind":"keyword"},{"kind":"text","text":" "},{"kind":"identifier","text":"CTAP2"}],"abstract":[{"text":"CTAP (Client to Authenticator Protocol) constants and structures","type":"text"}],"role":"symbol","url":"\/documentation\/yubikit\/ctap2","title":"CTAP2","kind":"symbol","identifier":"doc:\/\/yubikit-swift.YubiKit\/documentation\/YubiKit\/CTAP2"},"doc://yubikit-swift.YubiKit/documentation/YubiKit/CTAP2/MakeCredential/Parameters":{"kind":"symbol","role":"symbol","fragments":[{"kind":"keyword","text":"struct"},{"kind":"text","text":" "},{"kind":"identifier","text":"Parameters"}],"type":"topic","navigatorTitle":[{"kind":"identifier","text":"Parameters"}],"url":"\/documentation\/yubikit\/ctap2\/makecredential\/parameters","title":"CTAP2.MakeCredential.Parameters","identifier":"doc:\/\/yubikit-swift.YubiKit\/documentation\/YubiKit\/CTAP2\/MakeCredential\/Parameters","abstract":[{"text":"Parameters for the authenticatorMakeCredential command.","type":"text"}]},"doc://yubikit-swift.YubiKit/documentation/YubiKit/WebAuthn":{"type":"topic","navigatorTitle":[{"text":"WebAuthn","kind":"identifier"}],"fragments":[{"text":"enum","kind":"keyword"},{"text":" ","kind":"text"},{"text":"WebAuthn","kind":"identifier"}],"abstract":[{"type":"text","text":"WebAuthn (Web Authentication) namespace."}],"role":"symbol","url":"\/documentation\/yubikit\/webauthn","title":"WebAuthn","identifier":"doc:\/\/yubikit-swift.YubiKit\/documentation\/YubiKit\/WebAuthn","kind":"symbol"},"documentation-header.png":{"type":"image","alt":"YubiKeys in a row","identifier":"documentation-header.png","variants":[{"url":"\/images\/yubikit-swift.YubiKit\/documentation-header@2x.png","traits":["2x","light"]},{"url":"\/images\/yubikit-swift.YubiKit\/documentation-header~dark@2x.png","traits":["2x","dark"]}]},"doc://yubikit-swift.YubiKit/documentation/YubiKit/CTAP2/Extension/MakeCredential":{"type":"topic","navigatorTitle":[{"kind":"identifier","text":"MakeCredential"}],"fragments":[{"kind":"keyword","text":"enum"},{"kind":"text","text":" "},{"kind":"identifier","text":"MakeCredential"}],"abstract":[{"text":"Namespace for MakeCredential extension input protocol.","type":"text"}],"role":"symbol","url":"\/documentation\/yubikit\/ctap2\/extension\/makecredential","title":"CTAP2.Extension.MakeCredential","identifier":"doc:\/\/yubikit-swift.YubiKit\/documentation\/YubiKit\/CTAP2\/Extension\/MakeCredential","kind":"symbol"},"doc://yubikit-swift.YubiKit/documentation/YubiKit":{"kind":"symbol","role":"collection","images":[{"type":"icon","identifier":"documentation-header.png"}],"type":"topic","url":"\/documentation\/yubikit","title":"YubiKit","identifier":"doc:\/\/yubikit-swift.YubiKit\/documentation\/YubiKit","abstract":[{"type":"text","text":"Connect and run commands on the different applications on a YubiKey. The framework support connecting using NFC, Lightning and USB."}]},"doc://yubikit-swift.YubiKit/documentation/YubiKit/CTAP2/Extension":{"kind":"symbol","role":"symbol","fragments":[{"text":"enum","kind":"keyword"},{"text":" ","kind":"text"},{"text":"Extension","kind":"identifier"}],"type":"topic","navigatorTitle":[{"text":"Extension","kind":"identifier"}],"url":"\/documentation\/yubikit\/ctap2\/extension","title":"CTAP2.Extension","identifier":"doc:\/\/yubikit-swift.YubiKit\/documentation\/YubiKit\/CTAP2\/Extension","abstract":[{"text":"Namespace for CTAP2 extension types.","type":"text"}]},"doc://yubikit-swift.YubiKit/documentation/YubiKit/COSE/Algorithm":{"kind":"symbol","role":"symbol","fragments":[{"text":"enum","kind":"keyword"},{"text":" ","kind":"text"},{"text":"Algorithm","kind":"identifier"}],"type":"topic","navigatorTitle":[{"text":"Algorithm","kind":"identifier"}],"url":"\/documentation\/yubikit\/cose\/algorithm","title":"COSE.Algorithm","identifier":"doc:\/\/yubikit-swift.YubiKit\/documentation\/YubiKit\/COSE\/Algorithm","abstract":[{"type":"text","text":"COSE algorithm identifier for FIDO2\/WebAuthn."}]},"doc://yubikit-swift.YubiKit/documentation/YubiKit/WebAuthn/PublicKeyCredential/RPEntity":{"kind":"symbol","role":"symbol","fragments":[{"text":"struct","kind":"keyword"},{"text":" ","kind":"text"},{"text":"RPEntity","kind":"identifier"}],"type":"topic","navigatorTitle":[{"text":"RPEntity","kind":"identifier"}],"url":"\/documentation\/yubikit\/webauthn\/publickeycredential\/rpentity","title":"WebAuthn.PublicKeyCredential.RPEntity","identifier":"doc:\/\/yubikit-swift.YubiKit\/documentation\/YubiKit\/WebAuthn\/PublicKeyCredential\/RPEntity","abstract":[{"text":"Relying Party entity information.","type":"text"}]},"doc://yubikit-swift.YubiKit/documentation/YubiKit/CTAP2/MakeCredential/Parameters/Options-swift.struct":{"kind":"symbol","role":"symbol","fragments":[{"kind":"keyword","text":"struct"},{"kind":"text","text":" "},{"kind":"identifier","text":"Options"}],"type":"topic","navigatorTitle":[{"kind":"identifier","text":"Options"}],"url":"\/documentation\/yubikit\/ctap2\/makecredential\/parameters\/options-swift.struct","title":"CTAP2.MakeCredential.Parameters.Options","identifier":"doc:\/\/yubikit-swift.YubiKit\/documentation\/YubiKit\/CTAP2\/MakeCredential\/Parameters\/Options-swift.struct","abstract":[{"text":"Authenticator options for makeCredential.","type":"text"}]},"doc://yubikit-swift.YubiKit/documentation/YubiKit/WebAuthn/PublicKeyCredential/UserEntity":{"type":"topic","navigatorTitle":[{"text":"UserEntity","kind":"identifier"}],"fragments":[{"text":"struct","kind":"keyword"},{"text":" ","kind":"text"},{"text":"UserEntity","kind":"identifier"}],"abstract":[{"text":"User account entity information.","type":"text"}],"role":"symbol","url":"\/documentation\/yubikit\/webauthn\/publickeycredential\/userentity","title":"WebAuthn.PublicKeyCredential.UserEntity","kind":"symbol","identifier":"doc:\/\/yubikit-swift.YubiKit\/documentation\/YubiKit\/WebAuthn\/PublicKeyCredential\/UserEntity"},"doc://yubikit-swift.YubiKit/documentation/YubiKit/WebAuthn/PublicKeyCredential":{"type":"topic","navigatorTitle":[{"kind":"identifier","text":"PublicKeyCredential"}],"fragments":[{"text":"enum","kind":"keyword"},{"kind":"text","text":" "},{"kind":"identifier","text":"PublicKeyCredential"}],"abstract":[{"text":"Public Key Credential types and entities.","type":"text"}],"role":"symbol","url":"\/documentation\/yubikit\/webauthn\/publickeycredential","title":"WebAuthn.PublicKeyCredential","kind":"symbol","identifier":"doc:\/\/yubikit-swift.YubiKit\/documentation\/YubiKit\/WebAuthn\/PublicKeyCredential"},"doc://yubikit-swift.YubiKit/documentation/YubiKit/COSE":{"type":"topic","navigatorTitle":[{"text":"COSE","kind":"identifier"}],"fragments":[{"text":"enum","kind":"keyword"},{"text":" ","kind":"text"},{"text":"COSE","kind":"identifier"}],"abstract":[{"text":"COSE (CBOR Object Signing and Encryption) namespace.","type":"text"}],"role":"symbol","url":"\/documentation\/yubikit\/cose","title":"COSE","kind":"symbol","identifier":"doc:\/\/yubikit-swift.YubiKit\/documentation\/YubiKit\/COSE"},"doc://yubikit-swift.YubiKit/documentation/YubiKit/CTAP2/Extension/MakeCredential/Input":{"kind":"symbol","role":"symbol","fragments":[{"text":"struct","kind":"keyword"},{"text":" ","kind":"text"},{"text":"Input","kind":"identifier"}],"type":"topic","navigatorTitle":[{"text":"Input","kind":"identifier"}],"url":"\/documentation\/yubikit\/ctap2\/extension\/makecredential\/input","title":"CTAP2.Extension.MakeCredential.Input","identifier":"doc:\/\/yubikit-swift.YubiKit\/documentation\/YubiKit\/CTAP2\/Extension\/MakeCredential\/Input","abstract":[{"text":"An extension input for authenticatorMakeCredential.","type":"text"}]},"doc://yubikit-swift.YubiKit/documentation/YubiKit/CTAP2/MakeCredential/Parameters/init(clientDataHash:rp:user:pubKeyCredParams:excludeList:extensions:options:enterpriseAttestation:)":{"kind":"symbol","role":"symbol","fragments":[{"text":"init","kind":"identifier"},{"text":"(","kind":"text"},{"text":"clientDataHash","kind":"externalParam"},{"text":": ","kind":"text"},{"preciseIdentifier":"s:10Foundation4DataV","text":"Data","kind":"typeIdentifier"},{"text":", ","kind":"text"},{"text":"rp","kind":"externalParam"},{"text":": ","kind":"text"},{"preciseIdentifier":"s:7YubiKit8WebAuthnO","text":"WebAuthn","kind":"typeIdentifier"},{"text":".","kind":"text"},{"preciseIdentifier":"s:7YubiKit8WebAuthnO19PublicKeyCredentialO","text":"PublicKeyCredential","kind":"typeIdentifier"},{"text":".","kind":"text"},{"preciseIdentifier":"s:7YubiKit8WebAuthnO19PublicKeyCredentialO8RPEntityV","text":"RPEntity","kind":"typeIdentifier"},{"text":", ","kind":"text"},{"text":"user","kind":"externalParam"},{"text":": ","kind":"text"},{"preciseIdentifier":"s:7YubiKit8WebAuthnO","text":"WebAuthn","kind":"typeIdentifier"},{"text":".","kind":"text"},{"preciseIdentifier":"s:7YubiKit8WebAuthnO19PublicKeyCredentialO","text":"PublicKeyCredential","kind":"typeIdentifier"},{"text":".","kind":"text"},{"preciseIdentifier":"s:7YubiKit8WebAuthnO19PublicKeyCredentialO10UserEntityV","text":"UserEntity","kind":"typeIdentifier"},{"text":", ","kind":"text"},{"text":"pubKeyCredParams","kind":"externalParam"},{"text":": [","kind":"text"},{"preciseIdentifier":"s:7YubiKit4COSEO","text":"COSE","kind":"typeIdentifier"},{"text":".","kind":"text"},{"preciseIdentifier":"s:7YubiKit4COSEO9AlgorithmO","text":"Algorithm","kind":"typeIdentifier"},{"text":"], ","kind":"text"},{"text":"excludeList","kind":"externalParam"},{"text":": [","kind":"text"},{"preciseIdentifier":"s:7YubiKit8WebAuthnO","text":"WebAuthn","kind":"typeIdentifier"},{"text":".","kind":"text"},{"preciseIdentifier":"s:7YubiKit8WebAuthnO19PublicKeyCredentialO","text":"PublicKeyCredential","kind":"typeIdentifier"},{"text":".","kind":"text"},{"preciseIdentifier":"s:7YubiKit8WebAuthnO19PublicKeyCredentialO10DescriptorV","text":"Descriptor","kind":"typeIdentifier"},{"text":"]?, ","kind":"text"},{"text":"extensions","kind":"externalParam"},{"text":": [","kind":"text"},{"preciseIdentifier":"s:7YubiKit5CTAP2O","text":"CTAP2","kind":"typeIdentifier"},{"text":".","kind":"text"},{"preciseIdentifier":"s:7YubiKit5CTAP2O9ExtensionO","text":"Extension","kind":"typeIdentifier"},{"text":".","kind":"text"},{"preciseIdentifier":"s:7YubiKit5CTAP2O9ExtensionO14MakeCredentialO","text":"MakeCredential","kind":"typeIdentifier"},{"text":".","kind":"text"},{"preciseIdentifier":"s:7YubiKit5CTAP2O9ExtensionO14MakeCredentialO5InputV","text":"Input","kind":"typeIdentifier"},{"text":"], ","kind":"text"},{"text":"options","kind":"externalParam"},{"text":": ","kind":"text"},{"preciseIdentifier":"s:7YubiKit5CTAP2O14MakeCredentialO10ParametersV7OptionsV","text":"Options","kind":"typeIdentifier"},{"text":"?, ","kind":"text"},{"text":"enterpriseAttestation","kind":"externalParam"},{"text":": ","kind":"text"},{"preciseIdentifier":"s:Si","text":"Int","kind":"typeIdentifier"},{"text":"?)","kind":"text"}],"type":"topic","url":"\/documentation\/yubikit\/ctap2\/makecredential\/parameters\/init(clientdatahash:rp:user:pubkeycredparams:excludelist:extensions:options:enterpriseattestation:)","title":"init(clientDataHash:rp:user:pubKeyCredParams:excludeList:extensions:options:enterpriseAttestation:)","identifier":"doc:\/\/yubikit-swift.YubiKit\/documentation\/YubiKit\/CTAP2\/MakeCredential\/Parameters\/init(clientDataHash:rp:user:pubKeyCredParams:excludeList:extensions:options:enterpriseAttestation:)","abstract":[]},"doc://yubikit-swift.YubiKit/documentation/YubiKit/CTAP2/MakeCredential":{"kind":"symbol","role":"symbol","fragments":[{"kind":"keyword","text":"enum"},{"kind":"text","text":" "},{"kind":"identifier","text":"MakeCredential"}],"type":"topic","navigatorTitle":[{"kind":"identifier","text":"MakeCredential"}],"url":"\/documentation\/yubikit\/ctap2\/makecredential","title":"CTAP2.MakeCredential","identifier":"doc:\/\/yubikit-swift.YubiKit\/documentation\/YubiKit\/CTAP2\/MakeCredential","abstract":[{"text":"Namespace for MakeCredential command types.","type":"text"}]}}}